{
  "name": "Liechtensteinklamm",
  "version": "0.1.0",
  "license": "MIT",
  "summary": "Liechtensteinklamm is an abstraction layer of UISplitViewController’s delegate methods.",
  "homepage": "https://github.com/mogstad/liechtensteinklamm",
  "authors": {
    "Bjarne Mogstad": "me@mogstad.co"
  },
  "source": {
    "git": "https://github.com/mogstad/liechtensteinklamm.git",
    "tag": "v0.1.0"
  },
  "platforms": {
    "ios": "8.0"
  },
  "source_files": "liechtensteinklamm/*.swift",
  "requires_arc": true
}
